ticlust/__init__.py
ticlust/__main__.py
ticlust/_version.py
ticlust/cli.py
ticlust/core_api.py
ticlust/install_hooks.py
ticlust/logger.py
ticlust/ticlust.py
ticlust/bin/vsearch
ticlust/ticlust_helper/__init__.py
ticlust/ticlust_helper/config.py
ticlust/ticlust_helper/get_vsearch.py
ticlust/ticlust_helper/utils.py
ticlust-1.0.8.dist-info/METADATA
ticlust-1.0.8.dist-info/WHEEL
ticlust-1.0.8.dist-info/entry_points.txt
ticlust-1.0.8.dist-info/top_level.txt
ticlust-1.0.8.dist-info/RECORD
