Metadata-Version: 2.4
Name: ticlust
Version: 1.0.8
Summary: Taxonomy Informed Clustering (TIC) is a tool for clustering bacterial sequences based on their taxonomy and hypothetically complete taxonomy levels.
Author: Mohsen Pourjam, Ilias Lagkouvardos
Author-email: Mohsen Pourjam <pourjam.cs@hotmial.com>, Ilias Lagkouvardos <ilias.lagkouvardos@gmail.com>
License: MIT
Project-URL: repository, https://github.com/MPourjam/TIClust
Requires-Python: >=3.6
Requires-Dist: pandas
Dynamic: author
Dynamic: requires-python
